torch_models/__init__.py
torch_models-0.0.7.dist-info/LICENSE
torch_models-0.0.7.dist-info/METADATA
torch_models-0.0.7.dist-info/WHEEL
torch_models-0.0.7.dist-info/top_level.txt
torch_models-0.0.7.dist-info/RECORD
